Workbook

Sheet Executive Dashboard
A1: Sales Performance & Customer Insights Dashboard
A3: TOTAL SALES (₹) | D3: TOTAL PROFIT (₹) | G3: TOTAL ORDERS | J3: AVG ORDER VALUE (₹)
A4: =SUM('Sales Data'!K4:K27) -> 879290 | D4: =SUM('Sales Data'!M4:M27) -> 215490 | G4: =COUNTA('Sales Data'!A4:A27) -> 24 | J4: =AVERAGE('Sales Data'!K4:K27) -> 36637.083
A7: Executive Data Storytelling & Key Findings
A8: • Revenue & Profit Drivers: Electronics continues to dominate revenue (approx 68%), with 4K Monitors and Standing Desks being the highest contributors.
A9: • High-Value Customers: Tony Stark and Wanda Maximoff emerge as top individual spenders, driving multi-item premium purchases.
A10: • Regional Breakdown: West and North regions show the highest order value per customer, whereas East has lower unit margins.
A11: • Discount Impact: What-If Analysis indicates increasing discounts beyond 10% significantly erodes net profitability without proportional volume gains.
A14: Task 7: Top 10 High-Value Customers (INDEX & MATCH Lookups)
A16: Rank | B16: Customer Name | C16: Total Purchase (₹)
A17: 1 | B17: =INDEX('Sales Data'!G4:G27, MATCH(LARGE('Sales Data'!K4:K27, 1), 'Sales Data'!K4:K27, 0)) -> Tony Stark | C17: =LARGE('Sales Data'!K4:K27, 1) -> 112640
A18: 2 | B18: =INDEX('Sales Data'!G4:G27, MATCH(LARGE('Sales Data'!K4:K27, 2), 'Sales Data'!K4:K27, 0)) -> Wanda Maximoff | C18: =LARGE('Sales Data'!K4:K27, 2) -> 75600
A19: 3 | B19: =INDEX('Sales Data'!G4:G27, MATCH(LARGE('Sales Data'!K4:K27, 3), 'Sales Data'!K4:K27, 0)) -> Laura Croft | C19: =LARGE('Sales Data'!K4:K27, 3) -> 71400
A20: 4 | B20: =INDEX('Sales Data'!G4:G27, MATCH(LARGE('Sales Data'!K4:K27, 4), 'Sales Data'!K4:K27, 0)) -> Julia Roberts | C20: =LARGE('Sales Data'!K4:K27, 4) -> 57600
A21: 5 | B21: =INDEX('Sales Data'!G4:G27, MATCH(LARGE('Sales Data'!K4:K27, 5), 'Sales Data'!K4:K27, 0)) -> Julia Roberts | C21: =LARGE('Sales Data'!K4:K27, 5) -> 57600
A22: 6 | B22: =INDEX('Sales Data'!G4:G27, MATCH(LARGE('Sales Data'!K4:K27, 6), 'Sales Data'!K4:K27, 0)) -> Victor Vance | C22: =LARGE('Sales Data'!K4:K27, 6) -> 55200
A23: 7 | B23: =INDEX('Sales Data'!G4:G27, MATCH(LARGE('Sales Data'!K4:K27, 7), 'Sales Data'!K4:K27, 0)) -> Sarah Connor | C23: =LARGE('Sales Data'!K4:K27, 7) -> 49680
A24: 8 | B24: =INDEX('Sales Data'!G4:G27, MATCH(LARGE('Sales Data'!K4:K27, 8), 'Sales Data'!K4:K27, 0)) -> Quinn Fabray | C24: =LARGE('Sales Data'!K4:K27, 8) -> 39900
A25: 9 | B25: =INDEX('Sales Data'!G4:G27, MATCH(LARGE('Sales Data'!K4:K27, 9), 'Sales Data'!K4:K27, 0)) -> Evan Wright | C25: =LARGE('Sales Data'!K4:K27, 9) -> 37800
A26: 10 | B26: =INDEX('Sales Data'!G4:G27, MATCH(LARGE('Sales Data'!K4:K27, 10), 'Sales Data'!K4:K27, 0)) -> Yennefer Vengerberg | C26: =LARGE('Sales Data'!K4:K27, 10) -> 35100

Sheet Sales Data
A1: Data Generation Timestamp:
A3: Order ID | B3: Date | C3: Region | D3: Shop Name | E3: Product Name | F3: Category | G3: Customer Name | H3: Unit Price (₹) | I3: Quantity | J3: Discount % | K3: Total Purchase (₹) | L3: Total Cost (₹) | M3: Profit (₹)
A4: ORD-2026-001 | B4: 2026-01-10 | C4: North | D4: Downtown Tech | E4: Wireless Mouse | F4: Electronics | G4: Alice Smith | H4: 2500 | I4: 5 | J4: 0.05 | K4: =H4*I4*(1-J4) -> 11875 | L4: =1800*I4 -> 9000 | M4: =K4-L4 -> 2875
A5: ORD-2026-002 | B5: 2026-01-12 | C5: South | D5: Uptown Goods | E5: Ergonomic Chair | F5: Furniture | G5: Bob Jones | H5: 15000 | I5: 2 | J5: 0.1 | K5: =H5*I5*(1-J5) -> 27000 | L5: =11000*I5 -> 22000 | M5: =K5-L5 -> 5000
A6: ORD-2026-003 | B6: 2026-01-15 | C6: East | D6: Metro Mart | E6: Mechanical Keyboard | F6: Electronics | G6: Charlie Brown | H6: 6500 | I6: 3 | J6: 0 | K6: =H6*I6*(1-J6) -> 19500 | L6: =4500*I6 -> 13500 | M6: =K6-L6 -> 6000
A7: ORD-2026-004 | B7: 2026-01-18 | C7: West | D7: Suburban Plaza | E7: 4K Monitor | F7: Electronics | G7: Diana Prince | H7: 32000 | I7: 1 | J7: 0.15 | K7: =H7*I7*(1-J7) -> 27200 | L7: =22000*I7 -> 22000 | M7: =K7-L7 -> 5200
A8: ORD-2026-005 | B8: 2026-01-22 | C8: North | D8: Downtown Tech | E8: Standing Desk | F8: Furniture | G8: Evan Wright | H8: 42000 | I8: 1 | J8: 0.1 | K8: =H8*I8*(1-J8) -> 37800 | L8: =28000*I8 -> 28000 | M8: =K8-L8 -> 9800
A9: ORD-2026-006 | B9: 2026-02-01 | C9: South | D9: Uptown Goods | E9: USB-C Hub | F9: Electronics | G9: Fiona Gallagher | H9: 3500 | I9: 4 | J9: 0.05 | K9: =H9*I9*(1-J9) -> 13300 | L9: =2100*I9 -> 8400 | M9: =K9-L9 -> 4900
A10: ORD-2026-007 | B10: 2026-02-05 | C10: East | D10: Metro Mart | E10: Desk Lamp | F10: Furniture | G10: George Clark | H10: 2800 | I10: 2 | J10: 0 | K10: =H10*I10*(1-J10) -> 5600 | L10: =1800*I10 -> 3600 | M10: =K10-L10 -> 2000
A11: ORD-2026-008 | B11: 2026-02-12 | C11: West | D11: Suburban Plaza | E11: Noise-Canceling Headphones | F11: Electronics | G11: Hannah Abbott | H11: 18000 | I11: 2 | J11: 0.08 | K11: =H11*I11*(1-J11) -> 33120 | L11: =12000*I11 -> 24000 | M11: =K11-L11 -> 9120
A12: ORD-2026-009 | B12: 2026-02-18 | C12: North | D12: Downtown Tech | E12: Wireless Mouse | F12: Electronics | G12: Ian Malcolm | H12: 2500 | I12: 8 | J12: 0.05 | K12: =H12*I12*(1-J12) -> 19000 | L12: =1800*I12 -> 14400 | M12: =K12-L12 -> 4600
A13: ORD-2026-010 | B13: 2026-02-25 | C13: South | D13: Uptown Goods | E13: 4K Monitor | F13: Electronics | G13: Julia Roberts | H13: 32000 | I13: 2 | J13: 0.1 | K13: =H13*I13*(1-J13) -> 57600 | L13: =22000*I13 -> 44000 | M13: =K13-L13 -> 13600
A14: ORD-2026-011 | B14: 2026-03-02 | C14: East | D14: Metro Mart | E14: Webcam 1080p | F14: Electronics | G14: Kevin Bacon | H14: 5500 | I14: 2 | J14: 0.05 | K14: =H14*I14*(1-J14) -> 10450 | L14: =3800*I14 -> 7600 | M14: =K14-L14 -> 2850
A15: ORD-2026-012 | B15: 2026-03-08 | C15: West | D15: Suburban Plaza | E15: Standing Desk | F15: Furniture | G15: Laura Croft | H15: 42000 | I15: 2 | J15: 0.15 | K15: =H15*I15*(1-J15) -> 71400 | L15: =28000*I15 -> 56000 | M15: =K15-L15 -> 15400
A16: ORD-2026-013 | B16: 2026-03-15 | C16: North | D16: Downtown Tech | E16: Paper Shredder | F16: Office Supplies | G16: Michael Scott | H16: 7500 | I16: 3 | J16: 0.05 | K16: =H16*I16*(1-J16) -> 21375 | L16: =5000*I16 -> 15000 | M16: =K16-L16 -> 6375
A17: ORD-2026-014 | B17: 2026-03-20 | C17: South | D17: Uptown Goods | E17: Desk Organizer | F17: Office Supplies | G17: Nina Williams | H17: 2200 | I17: 6 | J17: 0 | K17: =H17*I17*(1-J17) -> 13200 | L17: =1200*I17 -> 7200 | M17: =K17-L17 -> 6000
A18: ORD-2026-015 | B18: 2026-03-28 | C18: East | D18: Metro Mart | E18: Mechanical Keyboard | F18: Electronics | G18: Oscar Martinez | H18: 6500 | I18: 5 | J18: 0.1 | K18: =H18*I18*(1-J18) -> 29250 | L18: =4500*I18 -> 22500 | M18: =K18-L18 -> 6750
A19: ORD-2026-016 | B19: 2026-04-05 | C19: West | D19: Suburban Plaza | E19: Wireless Mouse | F19: Electronics | G19: Pam Beesly | H19: 2500 | I19: 12 | J19: 0.15 | K19: =H19*I19*(1-J19) -> 25500 | L19: =1800*I19 -> 21600 | M19: =K19-L19 -> 3900
A20: ORD-2026-017 | B20: 2026-04-12 | C20: North | D20: Downtown Tech | E20: Standing Desk | F20: Furniture | G20: Quinn Fabray | H20: 42000 | I20: 1 | J20: 0.05 | K20: =H20*I20*(1-J20) -> 39900 | L20: =28000*I20 -> 28000 | M20: =K20-L20 -> 11900
A21: ORD-2026-018 | B21: 2026-04-18 | C21: South | D21: Uptown Goods | E21: 4K Monitor | F21: Electronics | G21: Ryan Howard | H21: 32000 | I21: 2 | J21: 0.1 | K21: =H21*I21*(1-J21) -> 57600 | L21: =22000*I21 -> 44000 | M21: =K21-L21 -> 13600
A22: ORD-2026-019 | B22: 2026-04-25 | C22: East | D22: Metro Mart | E22: Noise-Canceling Headphones | F22: Electronics | G22: Sarah Connor | H22: 18000 | I22: 3 | J22: 0.08 | K22: =H22*I22*(1-J22) -> 49680 | L22: =12000*I22 -> 36000 | M22: =K22-L22 -> 13680
A23: ORD-2026-020 | B23: 2026-05-02 | C23: West | D23: Suburban Plaza | E23: 4K Monitor | F23: Electronics | G23: Tony Stark | H23: 32000 | I23: 4 | J23: 0.12 | K23: =H23*I23*(1-J23) -> 112640 | L23: =22000*I23 -> 88000 | M23: =K23-L23 -> 24640
A24: ORD-2026-021 | B24: 2026-05-10 | C24: North | D24: Downtown Tech | E24: Ergonomic Chair | F24: Furniture | G24: Victor Vance | H24: 15000 | I24: 4 | J24: 0.08 | K24: =H24*I24*(1-J24) -> 55200 | L24: =11000*I24 -> 44000 | M24: =K24-L24 -> 11200
A25: ORD-2026-022 | B25: 2026-05-15 | C25: South | D25: Uptown Goods | E25: Standing Desk | F25: Furniture | G25: Wanda Maximoff | H25: 42000 | I25: 2 | J25: 0.1 | K25: =H25*I25*(1-J25) -> 75600 | L25: =28000*I25 -> 56000 | M25: =K25-L25 -> 19600
A26: ORD-2026-023 | B26: 2026-05-20 | C26: East | D26: Metro Mart | E26: 4K Monitor | F26: Electronics | G26: Xavier Charles | H26: 32000 | I26: 1 | J26: 0.05 | K26: =H26*I26*(1-J26) -> 30400 | L26: =22000*I26 -> 22000 | M26: =K26-L26 -> 8400
A27: ORD-2026-024 | B27: 2026-05-28 | C27: West | D27: Suburban Plaza | E27: Mechanical Keyboard | F27: Electronics | G27: Yennefer Vengerberg | H27: 6500 | I27: 6 | J27: 0.1 | K27: =H27*I27*(1-J27) -> 35100 | L27: =4500*I27 -> 27000 | M27: =K27-L27 -> 8100
A28: Total | K28: =SUM(K4:K27) -> 879290 | M28: =SUM(M4:M27) -> 215490

Sheet What-If & Growth Analysis
A1: Task 2: WHAT-IF Analysis (Discount Impact on Profitability)
A3: Discount Scenario % | B3: Projected Total Sales (₹) | C3: Projected Total Profit (₹) | D3: Profit Margin %
A4: 0 | B4: =SUMPRODUCT('Sales Data'!H4:H27, 'Sales Data'!I4:I27) * (1 - A4) -> 971800 | C4: =B4 - SUM('Sales Data'!L4:L27) -> 308000 | D4: =C4 / B4 -> 0.31693764
A5: 0.05 | B5: =SUMPRODUCT('Sales Data'!H4:H27, 'Sales Data'!I4:I27) * (1 - A5) -> 923210 | C5: =B5 - SUM('Sales Data'!L4:L27) -> 259410 | D5: =C5 / B5 -> 0.28098699
A6: 0.08 | B6: =SUMPRODUCT('Sales Data'!H4:H27, 'Sales Data'!I4:I27) * (1 - A6) -> 894056 | C6: =B6 - SUM('Sales Data'!L4:L27) -> 230256 | D6: =C6 / B6 -> 0.25754091
A7: 0.1 | B7: =SUMPRODUCT('Sales Data'!H4:H27, 'Sales Data'!I4:I27) * (1 - A7) -> 874620 | C7: =B7 - SUM('Sales Data'!L4:L27) -> 210820 | D7: =C7 / B7 -> 0.24104182
A8: 0.12 | B8: =SUMPRODUCT('Sales Data'!H4:H27, 'Sales Data'!I4:I27) * (1 - A8) -> 855184 | C8: =B8 - SUM('Sales Data'!L4:L27) -> 191384 | D8: =C8 / B8 -> 0.22379277
A9: 0.15 | B9: =SUMPRODUCT('Sales Data'!H4:H27, 'Sales Data'!I4:I27) * (1 - A9) -> 826030 | C9: =B9 - SUM('Sales Data'!L4:L27) -> 162230 | D9: =C9 / B9 -> 0.19639723
A10: 0.2 | B10: =SUMPRODUCT('Sales Data'!H4:H27, 'Sales Data'!I4:I27) * (1 - A10) -> 777440 | C10: =B10 - SUM('Sales Data'!L4:L27) -> 113640 | D10: =C10 / B10 -> 0.14617205
A13: Task 5: Monthly Sales Growth & Custom Trend Formatting
A15: Month | B15: Sales (₹) | C15: MoM Growth % | D15: Trend Symbol (Custom Format)
A16: Jan | B16: 112500 | C16: 0 | D16: ➖ Baseline
A17: Feb | B17: 113100 | C17: =(B17-B16)/B16 -> 0.0053333333 | D17: =IF(C17>0, "▲ UP", IF(C17<0, "▼ DOWN", "➖ STABLE")) -> ▲ UP
A18: Mar | B18: 99600 | C18: =(B18-B17)/B17 -> -0.1193634 | D18: =IF(C18>0, "▲ UP", IF(C18<0, "▼ DOWN", "➖ STABLE")) -> ▼ DOWN
A19: Apr | B19: 111500 | C19: =(B19-B18)/B18 -> 0.11947791 | D19: =IF(C19>0, "▲ UP", IF(C19<0, "▼ DOWN", "➖ STABLE")) -> ▲ UP
A20: May | B20: 176800 | C20: =(B20-B19)/B19 -> 0.58565022 | D20: =IF(C20>0, "▲ UP", IF(C20<0, "▼ DOWN", "➖ STABLE")) -> ▲ UP

Sheet Analysis Toolpak & Stats
A1: Task 4: Descriptive Statistics Output (Sales Metric) | D1: Task 3: Linear Regression Output (Profit vs Sales)
A3: Statistic Metric | B3: Sales Value | D3: Regression Metric | E3: Value
A4: Mean | B4: 36637.08 | D4: Regression Statistics
A5: Standard Error | B5: 5128.17 | D5: Multiple R | E5: 0.9706
A6: Median | B6: 29825 | D6: R Square | E6: 0.9421
A7: Mode | B7: 57600 | D7: Adjusted R Square | E7: 0.9271
A8: Standard Deviation | B8: 25122.82 | D8: Standard Error | E8: 1350.5
A9: Sample Variance | B9: 6.3115594e+08 | D9: Observations | E9: 24
A10: Kurtosis | B10: 2.28
A11: Skewness | B11: 1.38 | D11: Parameter Coefficients
A12: Range | B12: 107040 | D12: Intercept (a) | E12: 1036.61
A13: Minimum | B13: 5600 | D13: Slope / Sales Coeff (b) | E13: 0.2168
A14: Maximum | B14: 112640 | D14: Regression Equation | E14: Profit = 0.2168 * Sales + (1036.61)
A15: Sum | B15: 879290
A16: Count | B16: 24

Sheet Pivot Table & Charts
A1: Task 8: Pivot Table - Total Sales by Region and Product Category
A3: Region | B3: Electronics | C3: Furniture | D3: Office Supplies | E3: Grand Total
A4: East | B4: 139280 | C4: 5600 | D4: 0 | E4: 144880
A5: North | B5: 30875 | C5: 132900 | D5: 21375 | E5: 185150
A6: South | B6: 128500 | C6: 102600 | D6: 13200 | E6: 244300
A7: West | B7: 233560 | C7: 71400 | D7: 0 | E7: 304960
A8: Grand Total | B8: =SUM(B4:B7) -> 532215 | C8: =SUM(C4:C7) -> 312500 | D8: =SUM(D4:D7) -> 34575 | E8: =SUM(E4:E7) -> 879290
